setup.cfg
setup.py
chef_gae/__init__.py
chef_gae/chef.py
chef_gae/encoder.py
chef_gae.egg-info/PKG-INFO
chef_gae.egg-info/SOURCES.txt
chef_gae.egg-info/dependency_links.txt
chef_gae.egg-info/requires.txt
chef_gae.egg-info/top_level.txt
chef_gae/tests/__init__.py
chef_gae/tests/sample_data.py
chef_gae/tests/test_client.py
chef_gae/tests/test_encode.py