Metadata-Version: 1.1
Name: chef-gae
Version: 1.0.3
Summary: A GAE-Friendly wrapper for the chef API
Home-page: https://github.com/thedataincubator/chef_gae
Author: Christian Moscardi
Author-email: christian@thedataincubator.com
License: MIT
Keywords: google appengine pycrypto chef server devops
Platform: UNKNOWN
Classifier: Development Status :: 4 - Beta
Classifier: Intended Audience :: Developers
Classifier: License :: OSI Approved :: MIT License
Classifier: Programming Language :: Python :: 2
Classifier: Programming Language :: Python :: 2.6
Classifier: Programming Language :: Python :: 2.7
